{
  "required"          : true,
  "minVersion"        : "0.8",
  "package"           : "mcp.mobius.waila.jaded.mixin",
  "plugin"            : "mcp.mobius.waila.jaded.JadeWailaMixinPlugin",
  "compatibilityLevel": "JAVA_16",
  "refmap"            : "wthit.refmap.json",
  "mixins"            : [
    "AccessPluginConfig",
    "AccessWailaClientRegistration",
    "AccessWailaCommonRegistration",
    "MixinCommonProxy"
  ],
  "client"            : [],
  "injectors"         : {
    "defaultRequire": 1
  }
}
